README.rst
setup.py
speedcurve/__init__.py
speedcurve/deployments.py
speedcurve/exceptions.py
speedcurve/models.py
speedcurve/notes.py
speedcurve/null.py
speedcurve/session.py
speedcurve/sites.py
speedcurve/speedcurve.py
speedcurve/tests.py
speedcurve/urls.py
speedcurve.py.egg-info/PKG-INFO
speedcurve.py.egg-info/SOURCES.txt
speedcurve.py.egg-info/dependency_links.txt
speedcurve.py.egg-info/requires.txt
speedcurve.py.egg-info/top_level.txt