Metadata-Version: 1.0
Name: speedcurve.py
Version: 0.2.3
Summary: Python wrapper for Speedcurve API(https://api.speedcurve.com/)
Home-page: https://speedcurvepy.readthedocs.org
Author: Matt Chung
Author-email: itsmemattchung@gmail.com
License: UNKNOWN
Platform: UNKNOWN
